{
  "words": [
    {
      "id": "one",
      "en": "one"
    },
    {
      "id": "two",
      "en": "two"
    },
    {
      "id": "three",
      "en": "three"
    },
    {
      "id": "four",
      "en": "four"
    },
    {
      "id": "five",
      "en": "five"
    },
    {
      "id": "six",
      "en": "six"
    },
    {
      "id": "seven",
      "en": "seven"
    },
    {
      "id": "eight",
      "en": "eight"
    },
    {
      "id": "nine",
      "en": "nine"
    },
    {
      "id": "ten",
      "en": "ten"
    },
    {
      "id": "man",
      "en": "man"
    },
    {
      "id": "woman",
      "en": "woman"
    },
    {
      "id": "people",
      "en": "people"
    },
    {
      "id": "head",
      "en": "head"
    },
    {
      "id": "mouth",
      "en": "mouth"
    },
    {
      "id": "nose",
      "en": "nose"
    },
    {
      "id": "ear",
      "en": "ear"
    },
    {
      "id": "water",
      "en": "water"
    },
    {
      "id": "rain",
      "en": "rain"
    },
    {
      "id": "name",
      "en": "name"
    },
    {
      "id": "come",
      "en": "come"
    },
    {
      "id": "go",
      "en": "go"
    },
    {
      "id": "speak",
      "en": "speak"
    }
  ],
  "languages": {
    "hausa": {
      "name": "Hausa",
      "words": {
        "one": "ɗaya",
        "two": "biyu",
        "three": "uku",
        "four": "huɗu",
        "five": "biyar",
        "six": "shida",
        "seven": "bakwai",
        "eight": "takwas",
        "nine": "tara",
        "ten": "goma",
        "man": "mutum",
        "woman": "mace",
        "people": "mutane",
        "head": "kai",
        "mouth": "baki",
        "nose": "hanci",
        "ear": "kunne",
        "water": "ruwa",
        "rain": "ruwan sama",
        "name": "suna",
        "come": "zo",
        "go": "tafi",
        "speak": "yi magana"
      }
    },
    "yoruba": {
      "name": "Yoruba",
      "words": {
        "one": "ọ̀kan",
        "two": "èjì",
        "three": "ẹ̀ta",
        "four": "ẹ̀rin",
        "five": "àrún",
        "six": "ẹ̀fà",
        "seven": "èje",
        "eight": "ẹ̀jọ",
        "nine": "ẹ̀sán",
        "ten": "ẹ̀wá",
        "man": "ọkùnrin",
        "woman": "obìnrin",
        "people": "ènìyàn",
        "head": "orí",
        "mouth": "ẹnu",
        "nose": "imú",
        "ear": "etí",
        "water": "omi",
        "rain": "òjò",
        "name": "orúkọ",
        "come": "wá",
        "go": "lọ",
        "speak": "sọ̀rọ̀"
      }
    },
    "igbo": {
      "name": "Igbo",
      "words": {
        "one": "otu",
        "two": "abụọ",
        "three": "atọ",
        "four": "anọ",
        "five": "ise",
        "six": "isii",
        "seven": "asaa",
        "eight": "asato",
        "nine": "itoolu",
        "ten": "ìri",
        "man": "nwoke",
        "woman": "nwanyị",
        "people": "ndị mmadụ",
        "head": "isi",
        "mouth": "ọnụ",
        "nose": "imi",
        "ear": "ntị",
        "water": "mmiri",
        "rain": "mmiri ozuzo",
        "name": "aha",
        "come": "bịa",
        "go": "gaa",
        "speak": "kwuo"
      }
    },
    "fulfulde": {
      "name": "Fulani (Fulfulde)",
      "words": {
        "one": "gooto",
        "two": "ɗiɗi",
        "three": "tati",
        "four": "nayi",
        "five": "joyi",
        "six": "jeegom",
        "seven": "jeeɗiɗi",
        "eight": "jeetati",
        "nine": "jeenayi",
        "ten": "sappo",
        "man": "gorko",
        "woman": "debbo",
        "people": "yimɓe",
        "head": "hoore",
        "mouth": "hunnduko",
        "nose": "hinere",
        "ear": "nowru",
        "water": "ndiyam",
        "rain": "toɓo",
        "name": "innde",
        "speak": "wowlude"
      }
    },
    "edo": {
      "name": "Edo",
      "words": {
        "one": "ọkpa",
        "two": "eva",
        "three": "eha",
        "four": "enẹn",
        "five": "isẹn",
        "six": "ehan",
        "seven": "ihinron",
        "eight": "erenren",
        "nine": "ihinrin",
        "ten": "igbe",
        "man": "okpia",
        "woman": "okhuo",
        "people": "emwan",
        "head": "uhunmwu",
        "mouth": "unu",
        "nose": "ihue",
        "ear": "ehọ",
        "water": "amẹ",
        "rain": "amẹ nọrhọ",
        "name": "eni",
        "come": "do",
        "go": "ghìan",
        "speak": "ta"
      }
    },
    "idoma": {
      "name": "Idoma",
      "words": {
        "one": "eye",
        "two": "epa",
        "three": "eta",
        "four": "ene",
        "five": "eho",
        "six": "ehili",
        "seven": "ahapa",
        "eight": "ahata",
        "nine": "ahane",
        "ten": "igwo",
        "man": "onyilo",
        "woman": "onya",
        "people": "ache",
        "head": "eyi",
        "mouth": "okonu",
        "nose": "enwu",
        "ear": "aho",
        "water": "enkpo",
        "rain": "owo",
        "name": "iye",
        "come": "waa",
        "go": "nyo",
        "speak": "ka"
      }
    },
    "ibibio": {
      "name": "Ibibio",
      "words": {
        "one": "kiet",
        "two": "iba",
        "three": "ita",
        "four": "inan",
        "five": "ition",
        "six": "itiokiet",
        "seven": "itiaba",
        "eight": "itiaita",
        "nine": "usukkiet",
        "ten": "duop",
        "man": "eden",
        "woman": "awowan",
        "people": "awo",
        "head": "ibuot",
        "mouth": "inua",
        "nose": "iwo",
        "ear": "uton",
        "water": "mmon",
        "rain": "edim",
        "name": "enyin",
        "come": "di",
        "speak": "tan",
        "go": "ka"
      }
    },
    "ijaw": {
      "name": "Ijaw (Izon)",
      "words": {
        "one": "kẹnị",
        "two": "mamụ",
        "three": "tarụ",
        "four": "noin",
        "five": "sonron",
        "six": "sondie",
        "seven": "sonoma",
        "eight": "ninghini",
        "nine": "ise",
        "ten": "oi",
        "man": "owei",
        "woman": "eré",
        "people": "uto",
        "head": "tibii",
        "mouth": "bibi",
        "nose": "nini",
        "ear": "beri",
        "water": "beni",
        "rain": "osuo",
        "name": "ere"
      }
    },
    "tiv": {
      "name": "Tiv",
      "words": {
        "one": "mom",
        "two": "uhar",
        "three": "utar",
        "four": "unyiin",
        "five": "utaan",
        "six": "ateratar",
        "seven": "utaankaruhar",
        "eight": "anigheni",
        "nine": "utankarunyiin",
        "ten": "pue",
        "man": "numsor",
        "woman": "kwase",
        "people": "ior",
        "head": "ityough",
        "mouth": "dza",
        "nose": "ihinga",
        "ear": "uto",
        "water": "ngerem",
        "rain": "uwula",
        "name": "iti"
      }
    },
    "ikwerre": {
      "name": "Ikwerre",
      "words": {
        "one": "otu",
        "two": "ẹbo",
        "three": "ẹto",
        "four": "ẹno",
        "five": "isne",
        "six": "isunu",
        "seven": "ẹsau",
        "eight": "ẹsato",
        "nine": "tolu",
        "ten": "nri",
        "man": "nyeruka",
        "woman": "nyerinya",
        "people": "nde badnu",
        "head": "ishi",
        "mouth": "ọnụ",
        "nose": "imi",
        "ear": "msi",
        "water": "mini",
        "rain": "olu",
        "name": "awhna",
        "come": "bia",
        "speak": "kwu",
        "go": "zee"
      }
    },
    "kanuri": {
      "name": "Kanuri",
      "words": {
        "one": "tiló",
        "two": "indí",
        "three": "yaskǝ",
        "four": "dégǝ",
        "five": "úgù",
        "six": "ɑrɑskǝ",
        "seven": "túlùr",
        "eight": "wuskú",
        "nine": "lǝgár",
        "ten": "megú",
        "man": "kwâ",
        "woman": "kámú",
        "people": "kâm",
        "head": "kə̀lâ",
        "mouth": "cî",
        "nose": "kə́nzà",
        "ear": "sə́mò",
        "water": "njî",
        "rain": "də̀lágə̀"
      }
    },
    "swahili": {
      "name": "Swahili",
      "words": {
        "one": "moja",
        "two": "mbili",
        "three": "tatu",
        "four": "nne",
        "five": "tano",
        "six": "sita",
        "seven": "saba",
        "eight": "nane",
        "nine": "tisa",
        "ten": "kumi",
        "man": "mwanaume",
        "woman": "mwanamke",
        "people": "watu",
        "head": "kichwa",
        "mouth": "mdomo",
        "nose": "pua",
        "ear": "sikio",
        "water": "maji",
        "rain": "mvua",
        "name": "jina",
        "come": "kuja",
        "go": "kwenda",
        "speak": "kusema"
      }
    },
    "luganda": {
      "name": "Luganda",
      "words": {
        "one": "emu",
        "two": "bbiri",
        "three": "ssatu",
        "four": "nnya",
        "five": "ttaano",
        "six": "mukaaga",
        "seven": "musanvu",
        "eight": "munaana",
        "nine": "mwenda",
        "ten": "kkumi",
        "man": "omusajja",
        "woman": "omukazi",
        "people": "abantu",
        "head": "omutwe",
        "mouth": "akamwa",
        "nose": "ennyindo",
        "ear": "okutu",
        "water": "amazzi",
        "rain": "enkuba",
        "name": "erinnya",
        "come": "jja",
        "go": "genda",
        "speak": "yogera"
      }
    }
  }
}